multilang_summarizer/__init__.py
multilang_summarizer/entropy.py
multilang_summarizer/lcs.py
multilang_summarizer/lemmatizer.py
multilang_summarizer/readability.py
multilang_summarizer/spanish_syllabicator.py
multilang_summarizer/summarizer.py
multilang_summarizer/tfidf.py
multilang_summarizer/languages/lemmatization-ast.txt
multilang_summarizer/languages/lemmatization-bg.txt
multilang_summarizer/languages/lemmatization-ca.txt
multilang_summarizer/languages/lemmatization-cs.txt
multilang_summarizer/languages/lemmatization-cy.txt
multilang_summarizer/languages/lemmatization-de.txt
multilang_summarizer/languages/lemmatization-en.txt
multilang_summarizer/languages/lemmatization-es.txt
multilang_summarizer/languages/lemmatization-et.txt
multilang_summarizer/languages/lemmatization-fa.txt
multilang_summarizer/languages/lemmatization-fr.txt
multilang_summarizer/languages/lemmatization-ga.txt
multilang_summarizer/languages/lemmatization-gd.txt
multilang_summarizer/languages/lemmatization-gl.txt
multilang_summarizer/languages/lemmatization-gv.txt
multilang_summarizer/languages/lemmatization-hu.txt
multilang_summarizer/languages/lemmatization-it.txt
multilang_summarizer/languages/lemmatization-pt.txt
multilang_summarizer/languages/lemmatization-ro.txt
multilang_summarizer/languages/lemmatization-sk.txt
multilang_summarizer/languages/lemmatization-sl.txt
multilang_summarizer/languages/lemmatization-sv.txt
multilang_summarizer/languages/lemmatization-uk.txt
multilang_summarizer-1.7.dist-info/LICENSE
multilang_summarizer-1.7.dist-info/METADATA
multilang_summarizer-1.7.dist-info/WHEEL
multilang_summarizer-1.7.dist-info/top_level.txt
multilang_summarizer-1.7.dist-info/RECORD
