Metadata-Version: 2.1
Name: multilang-summarizer
Version: 1.7
Summary: Multilanguage summarizer, intended to improve text readability
Home-page: http://www.arturocuriel.com
Author: Arturo Curiel
Author-email: me@arturocuriel.com
License: GPLv3
Download-URL: https://github.com/elmugrearturo/multilang_summarizer/archive/1.7.tar.gz
Keywords: SUMMARIZATION,MULTILANGUAGE,RULE-BASED
Platform: UNKNOWN
Classifier: Development Status :: 4 - Beta
Classifier: Intended Audience :: Developers
Classifier: Topic :: Software Development :: Build Tools
Classifier: License :: OSI Approved :: GNU General Public License v3 (GPLv3)
Classifier: Programming Language :: Python :: 3
Classifier: Programming Language :: Python :: 3.4
Classifier: Programming Language :: Python :: 3.5
Classifier: Programming Language :: Python :: 3.6
Classifier: Programming Language :: Python :: 3.7
Requires-Dist: nltk
Requires-Dist: pyphen
Requires-Dist: textstat
Requires-Dist: sentence-splitter
Requires-Dist: numpy
